Workbook
Name end_time: '[1]Distributed Team Meeting Plan'!$E$6
Name LEADS_table: [2]!CRM_Leads_table[#Data]
Name start_time: '[1]Distributed Team Meeting Plan'!$D$6
Name Type: '[3]Maintenance Work Order'!#REF!
Name valHighlight: #REF!
Name BASE: #REF!

Sheet Registro
A1: Documento | B1: Estado de conciliación | C1: n° de documento | D1: Razón social | E1: Fecha | F1: Banco | G1: Tipo de pago | H1: Neto / liquido | I1: IVA | J1: Imposiciones/retenciones | K1: Total | L1: Proyecto | M1: Condición | N1: Tipo de flujo | O1: Descripción | P1: Documento 1 | Q1: Documento 2 | R1: Documento 3 | S1: Columna 1
A2: BOLETA DE HONORARIOS | B2: CONCILIADO | C2: 7 | D2: Pago: Humberto Alejandro Ojeda | E2: 46331 | F2: B Chile | G2: Debito | H2: 50000 | I2: 0 | J2: 8997 | K2: =H2+J2 -> 58997 | L2: 0.1 Concon - 2594-230-COT26 | M2: COSTO | N2: FIJO | O2: Boleta de honorarios - Humberto Alejandro Ojeda | P2: BOLETA DE HONORARIOS ELECTRONICA N°7 HAOV | S2: x
A3: COMPROBANTE DE PAGO | B3: PENDIENTE | C3: ---- | D3: Suscripcion Google LLC | E3: 46302 | H3: 1504 | I3: 286 | J3: 0 | K3: =H3+I3 -> 1790 | L3: GENERAL | M3: GASTO | N3: FIJO | O3: Cobro por suscripcion Google LLC 100gb | P3: CUENTA GOOGLE JULIO 2026 | S3: x
A4: BOLETA DE HONORARIOS | B4: PENDIENTE | C4: 7 | D4: Pago: Angel Hernan Pizarro Pavez | E4: 46272 | H4: 650000 | I4: 0 | J4: 116962 | K4: =H4+J4 -> 766962 | L4: GENERAL | M4: GASTO | N4: VARIABLE | O4: Boleta de honorarios - Angel Hernan Pizarro Pavez | P4: BOLETA DE HONORARIOS ELECTRONICA N°7 AHPP
A5: BOLETA | B5: PENDIENTE | D5: Soc. Conc. Ruta 5 Talca-Chillán S.A. | E5: 46271 | G5: Efectivo | H5: 800 | I5: 0 | J5: 0 | K5: 800 | L5: GENERAL | M5: GASTO | N5: VARIABLE | O5: PEAJE Plaza: San Carlos Sur | P5: Pago Peajes Ruta 5 Talca-Chillán 06-09-26
A6: BOLETA | B6: PENDIENTE | D6: Soc. Conc. Ruta 5 Talca-Chillán S.A. | E6: 46271 | G6: Efectivo | H6: 800 | I6: 0 | J6: 0 | K6: 800 | L6: GENERAL | M6: GASTO | N6: VARIABLE | O6: PEAJE Plaza: Chillán Norte | P6: Pago Peajes Ruta 5 Talca-Chillán 06-09-26
A7: BOLETA | B7: PENDIENTE | D7: Soc. Conc. Ruta 5 Talca-Chillán S.A. | E7: 46271 | G7: Efectivo | H7: 800 | I7: 0 | J7: 0 | K7: 800 | L7: GENERAL | M7: GASTO | N7: VARIABLE | O7: PEAJE Plaza: San Carlos Sur | P7: Pago Peaje Plaza San Carlos 06-09-26
A8: BOLETA | B8: PENDIENTE | C8: 1241909 | D8: Empresa Nacional de Energía ENEX S.A | E8: 46271 | G8: Efectivo | H8: 15620 | I8: =H8*19% -> 2967.8 | J8: 0 | K8: =(H8+I8)-1844 -> 16743.8 | L8: GENERAL | M8: GASTO | N8: VARIABLE | O8: Combustible Petróleo Diesel | P8: ENEX S.A. BOLETA N°1241909
A9: BOLETA | B9: PENDIENTE | C9: 2689791942 | D9: LIDER | E9: 46269 | G9: Debito | H9: =K9/1.19 -> 88579.832 | I9: =H9*19% -> 16830.168 | J9: 0 | K9: 105410 | L9: GENERAL | M9: GASTO | N9: VARIABLE | O9: Compra Lider articulos varios | P9: LIDER BOLETA 2689791942 Estación central jornada 1
A10: BOLETA | B10: PENDIENTE | C10: 2663056173 | D10: LIDER | E10: 46268 | G10: Debito | H10: =K10/1.19 -> 13176.471 | I10: =H10*19% -> 2503.5294 | J10: 0 | K10: 15680 | L10: GENERAL | M10: GASTO | N10: VARIABLE | O10: Compra Lider articulos de ferreteria | P10: LIDER BOLETA 2663056173 Maule Ambiental
A11: FACTURA | B11: PENDIENTE | C11: 149451576 | D11: SODIMAC S.A | E11: 46267 | H11: =K11/1.19 -> 5327.7311 | I11: =H11*19% -> 1012.2689 | J11: 0 | K11: 6340 | L11: GENERAL | M11: GASTO | N11: VARIABLE | O11: Tierra con abono natural | P11: F_149451576 SODIMAC S.A
A12: FACTURA | B12: PENDIENTE | C12: 149451577 | D12: SODIMAC S.A | E12: 46267 | H12: =K12/1.19 -> 2512.605 | I12: =H12*19% -> 477.39496 | J12: 0 | K12: 2990 | L12: GENERAL | M12: GASTO | N12: VARIABLE | O12: Set de 5 panos microfibra 30x40cm | P12: F_149451577 SODIMAC S.A
A13: FACTURA | B13: PENDIENTE | C13: 189 | D13: ESTUDIO CONTABLE C&V LIMITADA | E13: 46266 | G13: Credito | H13: 0 | I13: =H13*19% -> 0 | J13: 0 | K13: 67033 | L13: GENERAL | M13: GASTO | N13: VARIABLE | O13: Asesorias contables y RRHH | P13: F_189 ESTUDIO CONTABLE C&V LIMITADA
A14: FACTURA | B14: PENDIENTE | C14: 10570 | D14: KUPOS S.A. | E14: 46265 | H14: 0 | I14: =H14*19% -> 0 | J14: 0 | K14: 25850 | L14: GENERAL | M14: GASTO | N14: VARIABLE | O14: Pasajes terrestres agosto | P14: F_10570 KUPOS S.A
A15: BOLETA | B15: PENDIENTE | C15: 20088414 | D15: LAFLOTECOPIA EIRL | E15: 46265 | G15: Debito | H15: =K15/1.19 -> 9243.6975 | I15: =H15*19% -> 1756.3025 | J15: 0 | K15: 11000 | L15: GENERAL | M15: GASTO | N15: VARIABLE | O15: Compra LAFLOTECOPIA EIRL | P15: 46236
A16: BOLETA | B16: PENDIENTE | C16: 20059394 | D16: COMERCIAL AIPING LTD | E16: 46265 | G16: Debito | H16: =K16/1.19 -> 10084.034 | I16: =H16*19% -> 1915.9664 | J16: 0 | K16: 12000 | L16: GENERAL | M16: GASTO | N16: VARIABLE | O16: Compra Comercial Aiping LTD | P16: 46236
A17: BOLETA | B17: PENDIENTE | C17: 3196790 | D17: COPEC S.A. | E17: 46262 | G17: Credito | H17: 14264 | I17: 2805 | J17: 0 | K17: 15794 | L17: GENERAL | M17: GASTO | N17: VARIABLE | O17: Combustible Petróleo Diesel | P17: COPEC S.A. BOLETA 3196790
A18: FACTURA | B18: PENDIENTE | C18: 1284438 | D18: Electrónica Retail Limitada | E18: 46261 | G18: Debito | H18: =K18/1.19 -> 73924.37 | I18: =H18*19% -> 14045.63 | J18: 0 | K18: 87970 | L18: GENERAL | M18: GASTO | N18: VARIABLE | O18: Articulos electrónicos | P18: 46236
A19: BOLETA | B19: PENDIENTE | C19: 470091898 | D19: Mall Marina Viña | E19: 46261 | G19: Debito | H19: =K19/1.19 -> 1680.6723 | I19: =H19*19% -> 319.32773 | J19: 0 | K19: 2000 | L19: GENERAL | M19: GASTO | N19: VARIABLE | O19: BOU Shortterm Parking | P19: 46236
A20: BOLETA | B20: PENDIENTE | C20: 2620638606 | D20: LIDER | E20: 46260 | G20: Debito | H20: =K20/1.19 -> 10688.235 | I20: =H20*19% -> 2030.7647 | J20: 0 | K20: 12719 | L20: GENERAL | M20: GASTO | N20: VARIABLE | O20: Compra Lider articulos de oficina | P20: LIDER BOLETA 2620638606 Maule Ambiental 1
A21: FACTURA | B21: PENDIENTE | C21: 38950212 | D21: EASY RETAIL S.A. | E21: 46259 | G21: Efectivo | H21: =K21/1.19 -> 22680.672 | I21: =H21*19% -> 4309.3277 | J21: 0 | K21: 26990 | L21: GENERAL | M21: GASTO | N21: VARIABLE | O21: Articulos de Ferreteria | P21: 46236
A22: FACTURA | B22: PENDIENTE | C22: 38950212 | D22: EASY RETAIL S.A. | E22: 46259 | G22: Debito | H22: =K22/1.19 -> 52092.437 | I22: =H22*19% -> 9897.563 | J22: 0 | K22: 61990 | L22: GENERAL | M22: GASTO | N22: VARIABLE | O22: Articulos de Ferreteria | P22: 46236
A23: FACTURA | B23: PENDIENTE | C23: 95151 | D23: COPEC - COMERCIAL Y DISTRIBUIDORA SEPULVEDA | E23: 46259 | G23: Debito | H23: 9332 | I23: =H23*19% -> 1773.08 | J23: 0 | K23: =(H23+I23)+4402-507 -> 15000.08 | L23: GENERAL | M23: GASTO | N23: VARIABLE | O23: Combustible Gasolina 93 | P23: 46236
B24: PENDIENTE | C24: 2508 240113462371 00013226631 | D24: ZOOM.COM 888-799-96 COMPRAS INT.VI | E24: 46258 | F24: BCI | G24: Credito | H24: =K24/1.19 -> 13235.924 | I24: =H24*19% -> 2514.8256 | J24: 0 | K24: 15750.75 | L24: GENERAL | M24: GASTO | N24: VARIABLE | O24: ZOOM.COM 888-799-96 COMPRAS INT.VI | P24: 2026-08-27_Movimientos_Tarjeta_5645_SERVICIOS DE INGENIERIA IVAN ANDRES ARRIAGADA BASCUNAN EIRL (9).pdf
A25: BOLETA | B25: PENDIENTE | C25: 273895 | D25: IMPORTADORA Y DISTRIBUIDORA GO-SHOP LTDA | E25: 46255 | H25: =K25/1.19 -> 10974.79 | I25: =H25*19% -> 2085.2101 | J25: 0 | K25: 13060 | L25: GENERAL | M25: GASTO | N25: VARIABLE | O25: Papel Fotográfico A4 y envío | P25: F_273895 GOSHOP
A26: FACTURA | B26: PENDIENTE | C26: 20136 | D26: DISTRIBUIDORA GALAXIA LIMITADA | E26: 46255 | H26: =K26/1.19 -> 8806.7227 | I26: =H26*19% -> 1673.2773 | J26: 0 | K26: 10480 | L26: GENERAL | M26: GASTO | N26: VARIABLE | O26: Resma Papel Carta 500hjs y envío | P26: F_20136 DISTRIBUIDORA GALAXIA
B27: PENDIENTE | C27: 2408 244921662341 00001852789 | D27: OPENAI*CHATGPT SUB - Internacional | E27: 46255 | F27: BCI | G27: Credito | H27: =K27/1.19 -> 15580.84 | I27: =H27*19% -> 2960.3597 | J27: 0 | K27: 18541.2 | L27: GENERAL | M27: GASTO | N27: FIJO | O27: OPENAI*CHATGPT SUB - Internacional | P27: 2026-08-27_Movimientos_Tarjeta_5645_SERVICIOS DE INGENIERIA IVAN ANDRES ARRIAGADA BASCUNAN EIRL (9).pdf
B28: PENDIENTE | C28: 2008 00000000 | D28: IMPUESTO DECRETO LEY 3475 TASA 0,066 % | E28: 46254 | F28: BCI | G28: Credito | H28: =K28/1.19 -> 45.378151 | I28: =H28*19% -> 8.6218487 | J28: 0 | K28: 54 | L28: GENERAL | M28: GASTO | N28: VARIABLE | O28: IMPUESTO DECRETO LEY 3475 TASA 0,066 % | P28: 2026-08-27_Movimientos_Tarjeta_5645_SERVICIOS DE INGENIERIA IVAN ANDRES ARRIAGADA BASCUNAN EIRL (9).pdf
B29: PENDIENTE | C29: 2008 00000000 | D29: COBRO ADM MENSUAL | E29: 46254 | F29: BCI | G29: Credito | H29: =K29/1.19 -> 3433.6134 | I29: =H29*19% -> 652.38655 | J29: 0 | K29: 4086 | L29: GENERAL | M29: GASTO | N29: FIJO | O29: COBRO ADM MENSUAL | P29: 2026-08-27_Movimientos_Tarjeta_5645_SERVICIOS DE INGENIERIA IVAN ANDRES ARRIAGADA BASCUNAN EIRL (9).pdf
B30: PENDIENTE | C30: 2008 00000000 | D30: INTERESES ROTATIVOS | E30: 46254 | F30: BCI | G30: Credito | H30: =K30/1.19 -> 2279.8319 | I30: =H30*19% -> 433.16807 | J30: 0 | K30: 2713 | L30: GENERAL | M30: GASTO | N30: VARIABLE | O30: INTERESES ROTATIVOS | P30: 2026-08-27_Movimientos_Tarjeta_5645_SERVICIOS DE INGENIERIA IVAN ANDRES ARRIAGADA BASCUNAN EIRL (9).pdf
A31: FACTURA | B31: PENDIENTE | C31: 5743514 | D31: FALABELLA RETAIL S.A. | E31: 46254 | H31: =K31/1.19 -> 134445.38 | I31: =H31*19% -> 25544.622 | J31: 0 | K31: 159990 | L31: GENERAL | M31: GASTO | N31: VARIABLE | O31: HP-IMPRESORA | P31: F_5743514 FALABELLA S.A
A32: FACTURA | B32: PENDIENTE | C32: 78345 | D32: COPEC - ESCOBAR Y DE DIEGO LIMITADA | E32: 46253 | G32: Debito | H32: 6376 | I32: 1211 | J32: 0 | K32: =(H32+I32)+3115-702 -> 10000 | L32: GENERAL | M32: GASTO | N32: VARIABLE | O32: Combustible Gasolina | P32: 46236
A33: FACTURA | B33: PENDIENTE | C33: 38841643 | D33: EASY RETAIL S.A. | E33: 46253 | G33: Debito | H33: =K33/1.19 -> 219512.61 | I33: =H33*19% -> 41707.395 | J33: 0 | K33: 261220 | L33: GENERAL | M33: GASTO | N33: VARIABLE | O33: Articulos de Ferreteria | P33: 46236
A34: FACTURA | B34: PENDIENTE | C34: 13341738 | D34: CHILEXPRESS S.A. | E34: 46253 | H34: =K34/1.19 -> 6714.2857 | I34: =H34*19% -> 1275.7143 | J34: 0 | K34: 7990 | L34: GENERAL | M34: GASTO | N34: VARIABLE | O34: Envío Chilexpress | P34: 46236
A35: FACTURA | B35: PENDIENTE | C35: 7799 | D35: GRABOCHILE SPA | E35: 46253 | H35: 667360 | I35: 126798 | J35: 0 | K35: =H35+I35 -> 794158 | L35: 0.8 Gestión Social Viña 2424-1046-COT26 | M35: COSTO | N35: VARIABLE | O35: Materiales de trabajo | P35: GABROCHILE SPA F_7799 | S35: x
B36: PENDIENTE | C36: 2008 90695554 | D36: LINKEDIN LINKEDIN LAS CONDES | E36: 46253 | F36: BCI | G36: Credito | H36: =K36/1.19 -> 73512.605 | I36: =H36*19% -> 13967.395 | J36: 0 | K36: 87480 | L36: GENERAL | M36: GASTO | N36: VARIABLE | O36: LINKEDIN LINKEDIN LAS CONDES | P36: 2026-08-27_Movimientos_Tarjeta_5645_SERVICIOS DE INGENIERIA IVAN ANDRES ARRIAGADA BASCUNAN EIRL (9).pdf
B37: PENDIENTE | C37: 1708 24011346 | D37: ANTHROPIC* CLAUDE S - Internacional | E37: 46251 | F37: BCI | G37: Credito | H37: =K37/1.19 -> 18541.202 | I37: =H37*19% -> 3522.8283 | J37: 0 | K37: 22064.03 | L37: GENERAL | M37: GASTO | N37: VARIABLE | O37: ANTHROPIC* CLAUDE S | P37: 2026-08-27_Movimientos_Tarjeta_5645_SERVICIOS DE INGENIERIA IVAN ANDRES ARRIAGADA BASCUNAN EIRL (9).pdf
B38: PENDIENTE | C38: 1808 11124076 | D38: SIMPLEDTE / PIRIOD SANTIAGO | E38: 46251 | F38: BCI | G38: Credito | H38: =K38/1.19 -> 71905.882 | I38: =H38*19% -> 13662.118 | J38: 0 | K38: 85568 | L38: GENERAL | M38: GASTO | N38: VARIABLE | O38: SIMPLEDTE / PIRIOD SANTIAGO | P38: 2026-08-27_Movimientos_Tarjeta_5645_SERVICIOS DE INGENIERIA IVAN ANDRES ARRIAGADA BASCUNAN EIRL (9).pdf
B39: PENDIENTE | C39: 1708 00000000 | D39: COMISIÓN COMPRA INTERNACIONAL | E39: 46251 | F39: BCI | G39: Credito | H39: =K39/1.19 -> 472.26891 | I39: =H39*19% -> 89.731092 | J39: 0 | K39: 562 | L39: GENERAL | M39: GASTO | N39: VARIABLE | O39: COMISIÓN COMPRA INTERNACIONAL | P39: 2026-08-27_Movimientos_Tarjeta_5645_SERVICIOS DE INGENIERIA IVAN ANDRES ARRIAGADA BASCUNAN EIRL (9).pdf
A40: FACTURA | B40: PENDIENTE | C40: 17CJFK4L-0004 | D40: Pago Invoice mensual | E40: 46248 | H40: 18320 | I40: 3500 | J40: 0 | K40: =H40+I40 -> 21820 | L40: GENERAL | M40: GASTO | N40: FIJO | O40: Suscripcion mensual | P40: F_17CJFK4L-0004 Invoice Agosto 14 | S40: x
A41: BOLETA | B41: PENDIENTE | C41: 3452345550 | D41: Jumbo | E41: 46248 | H41: 20991 | I41: 3989 | J41: 0 | K41: =H41+I41 -> 24980 | L41: 0.9 Paisajismo Coltauco 3997-148-COT26 | M41: COSTO | N41: VARIABLE | O41: Compra jumbo torta viena | P41: B_3452345550 JUMBO 14 AGOSTO | S41: x
A42: BOLETA | B42: PENDIENTE | C42: 22480204 | D42: Arcos de Valparaiso SPA ORD 946 | E42: 46247 | G42: Debito | H42: =K42/1.19 -> 6714.2857 | I42: =H42*19% -> 1275.7143 | J42: 0 | K42: 7990 | L42: GENERAL | M42: GASTO | N42: VARIABLE | O42: Alimentación | P42: 46236
A43: FACTURA | B43: PENDIENTE | C43: 149003983 | D43: Sodimac S.A | E43: 46247 | H43: 14457 | I43: 2748 | J43: 0 | K43: =H43+I43 -> 17205 | L43: 0.7 Taller coquimbo 2446-584-COT26 | M43: COSTO | N43: VARIABLE | O43: Compra de herramientas | P43: SODIMAC S.A F_149003983 | S43: x
A44: FACTURA | B44: PENDIENTE | C44: 149003977 | D44: Sodimac S.A | E44: 46247 | H44: 25882 | I44: 4918 | J44: 0 | K44: =H44+I44 -> 30800 | L44: 0.7 Taller coquimbo 2446-584-COT26 | M44: COSTO | N44: VARIABLE | O44: Compra de herramientas de construccion MPD | P44: SODIMAC S.A F_149003977 | S44: x
A45: FACTURA | B45: PENDIENTE | C45: 94378 | D45: COPEC S.A | E45: 46246 | G45: Debito | H45: 20781 | I45: 3948 | J45: 0 | K45: =H45+I45+5271 -> 30000 | L45: 0.8 Gestión Social Viña 2424-1046-COT26 | M45: COSTO | N45: VARIABLE | O45: Combustible | P45: COPEC S.A F_94378 | S45: x
A46: BOLETA DE HONORARIOS | B46: CONCILIADO | C46: 76 | D46: Pago: Gary Henriquez Pinto | E46: 46246 | F46: B Chile | G46: Debito | H46: 254250 | I46: 0 | J46: 45750 | K46: =J46+H46 -> 300000 | L46: 0.9 Paisajismo Coltauco 3997-148-COT26 | M46: COSTO | N46: FIJO | O46: Boleta de honorarios - Gary Henriquez Pinto | P46: BOLETA DE HONORARIOS ELECTRONICA N°76 GEHP | S46: x
A47: FACTURA | B47: PENDIENTE | C47: 31437 | D47: =D48 -> Comercializadora y distribuidora de materiales de construccion Ltda | E47: 46245 | G47: Efectivo | H47: 15126 | I47: 2874 | J47: 0 | K47: =H47+I47 -> 18000 | L47: 0.8 Gestión Social Viña 2424-1046-COT26 | M47: COSTO | N47: VARIABLE | O47: Compra de Flange 200X200X4MM | P47: Comercializadora y distribuidora de materiales de construccion F_31437 | S47: x
A48: FACTURA | B48: PENDIENTE | C48: 31436 | D48: Comercializadora y distribuidora de materiales de construccion Ltda | E48: 46245 | G48: Efectivo | H48: 416891 | I48: 79209 | J48: 0 | K48: =H48+I48 -> 496100 | L48: 0.8 Gestión Social Viña 2424-1046-COT26 | M48: COSTO | N48: VARIABLE | O48: Compra de materiales de construccion (MPD) | P48: Comercializadora y distribuidora de materiales de construccion F_31436 | S48: x
B49: PENDIENTE | C49: 1108 24692166 | D49: GOOGLE *Google One - Internacional | E49: 46245 | F49: BCI | G49: Credito | H49: =K49/1.19 -> 1565.8739 | I49: =H49*19% -> 297.51605 | J49: 0 | K49: 1863.39 | L49: GENERAL | M49: GASTO | N49: VARIABLE | O49: GOOGLE *Google One | P49: 2026-08-27_Movimientos_Tarjeta_5645_SERVICIOS DE INGENIERIA IVAN ANDRES ARRIAGADA BASCUNAN EIRL (9).pdf
B50: PENDIENTE | C50: 1108 00000000 | D50: COMISIÓN COMPRA INTERNACIONAL | E50: 46245 | F50: BCI | G50: Credito | H50: =K50/1.19 -> 39.495798 | I50: =H50*19% -> 7.5042017 | J50: 0 | K50: 47 | L50: GENERAL | M50: GASTO | N50: VARIABLE | O50: COMISIÓN COMPRA INTERNACIONAL | P50: 2026-08-27_Movimientos_Tarjeta_5645_SERVICIOS DE INGENIERIA IVAN ANDRES ARRIAGADA BASCUNAN EIRL (9).pdf
A51: COMPROBANTE DE PAGO | B51: PENDIENTE | C51: --- | D51: Suscripcion mensual LLC | E51: 46244 | H51: 1504 | I51: 286 | J51: 0 | K51: =H51+I51 -> 1790 | L51: GENERAL | M51: GASTO | N51: FIJO | O51: Cobro por suscripcion mensual Google LLC 100Gb | P51: CUENTA GOOGLE AGOSTO 10 | S51: x
A52: FACTURA | B52: PENDIENTE | C52: 148957669 | D52: Sodimac S.A | E52: 46241 | H52: 4184 | I52: 796 | J52: 0 | K52: =H52+I52 -> 4980 | L52: 0.7 Taller coquimbo 2446-584-COT26 | M52: COSTO | N52: VARIABLE | O52: Compra de semillas mix | P52: SODIMAC S.A F_148957669 | S52: x
A53: FACTURA | B53: PENDIENTE | C53: 148957667 | D53: Sodimac S.A | E53: 46241 | H53: 2512 | I53: 478 | J53: 0 | K53: =H53+I53 -> 2990 | L53: 0.7 Taller coquimbo 2446-584-COT26 | M53: COSTO | N53: VARIABLE | O53: Compra de semillas mix medicinal SEMCU | P53: SODIMAC S.A F_148957667 | S53: x
A54: COMPROBANTE DE PAGO | B54: PENDIENTE | C54: 878984895 | D54: Lider Express compra Tijeras 13cm | E54: 46241 | G54: Debito | H54: 3361 | I54: 639 | J54: 0 | K54: =H54+I54 -> 4000 | L54: 0.7 Taller coquimbo 2446-584-COT26 | M54: COSTO | N54: VARIABLE | O54: Compra de tijeras supermercado lider express | P54: Lider Express 878984895 | S54: x
A55: BOLETA DE HONORARIOS | B55: CONCILIADO | C55: 1 | D55: Pago: Agustin Ignacion Miranda | E55: 46241 | F55: B Chile | G55: Debito | H55: 80512 | I55: 0 | J55: 14488 | K55: =H55+J55 -> 95000 | L55: 0.8 Gestión Social Viña 2424-1046-COT26 | M55: COSTO | N55: FIJO | O55: Boleta de honorarios - Agustin ignacion miranda | P55: BOLETA DE HONORARIOS ELECTRONICA N°1 AIML | S55: x
A56: BOLETA | B56: PENDIENTE | C56: 1208397 | D56: BALLENARY-SERVICIOS SPA RUT 77.468.183-3 | E56: 46240 | G56: Debito | H56: 13082 | I56: 2486 | J56: 0 | K56: =H56+I56-2467 -> 13101 | L56: GENERAL | M56: GASTO | N56: VARIABLE | O56: Combustible Petróleo | P56: BOLETA 1208397 BALLENARY-SERVICIOS SPA.pdf
A57: FACTURA | B57: PENDIENTE | C57: 94002 | D57: COPEC S.A | E57: 46240 | G57: Debito | H57: 17318 | I57: 3290 | J57: 0 | K57: =H57+I57+4392 -> 25000 | L57: 0.8 Gestión Social Viña 2424-1046-COT26 | M57: COSTO | N57: VARIABLE | O57: Combustible | P57: COPEC S.A F_94002 | S57: x
A58: FACTURA | B58: PENDIENTE | C58: 20398696 | D58: IMPERIAL S.A. | E58: 46240 | H58: 77319 | I58: 14691 | J58: 0 | K58: =H58+I58 -> 92010 | L58: 0.7 Taller coquimbo 2446-584-COT26 | M58: COSTO | N58: VARIABLE | O58: Materiales de trabajo | P58: IMPERIAL S.A. F_0020398696 | S58: x
A59: FACTURA | B59: PENDIENTE | C59: 21653319 | D59: Entel Servicios de ingenieria Ivan Andres | E59: 46239 | H59: ---- | I59: ---- | K59: ----- | L59: GENERAL | M59: GASTO | N59: FIJO | O59: Entel | P59: F_21653319 ENTEL | S59: x
A60: FACTURA | B60: PENDIENTE | C60: 236 | D60: Comercializadora horizonte 7 Limitada | E60: 46239 | H60: 67059 | I60: 12741 | J60: 0 | K60: =H60+I60 -> 79800 | L60: 0.8 Gestión Social Viña 2424-1046-COT26 | M60: COSTO | N60: VARIABLE | O60: Compra Venta Art hogar | P60: COMERCIALIZADORA HORIZONTE 7 LIMITADA F_236 | S60: x
B61: PENDIENTE | C61: 0508 00000000 | D61: TRASPASO DEUDA INTERNACIONAL | E61: 46239 | F61: BCI | G61: Credito | H61: =K61/1.19 -> 68754.622 | I61: =H61*19% -> 13063.378 | J61: 0 | K61: 81818 | L61: GENERAL | M61: GASTO | N61: VARIABLE | O61: TRASPASO DEUDA INTERNACIONAL | P61: 2026-08-27_Movimientos_Tarjeta_5645_SERVICIOS DE INGENIERIA IVAN ANDRES ARRIAGADA BASCUNAN EIRL (9).pdf | Q61: 2026-08-27_Movimientos_Tarjeta_5645_SERVICIOS DE INGENIERIA IVAN ANDRES ARRIAGADA BASCUNAN EIRL (1).pdf
B62: PENDIENTE | C62: 0508 01173910 | D62: PAGO PAC EN PESOS | E62: 46239 | F62: BCI | G62: Credito | H62: =K62/1.19 -> 216400 | I62: =H62*19% -> 41116 | J62: 0 | K62: 257516 | L62: GENERAL | M62: INGRESO NO OPERACIONAL | N62: VARIABLE | O62: PAGO PAC EN PESOS | P62: 2026-08-27_Movimientos_Tarjeta_5645_SERVICIOS DE INGENIERIA IVAN ANDRES ARRIAGADA BASCUNAN EIRL (1).pdf
A63: FACTURA | B63: PENDIENTE | C63: 93853 | D63: COPEC S.A. | E63: 46238 | G63: Debito | H63: 13783 | I63: 2619 | J63: 0 | K63: =H63+I63+3598 -> 20000 | L63: 0.8 Gestión Social Viña 2424-1046-COT26 | M63: COSTO | N63: VARIABLE | O63: Combustible | P63: COPEC S.A. F_938853 | S63: x
A64: COMPROBANTE DE TRANSFERENCIA | B64: PENDIENTE | C64: 45937782 | D64: App-Traspaso a: A. Grabochile Spa | E64: 46237 | F64: BCI | G64: Debito | H64: =K64/1.19 -> 333679.83 | I64: =H64*19% -> 63399.168 | J64: 0 | K64: 397079 | L64: 0.8 Gestión Social Viña 2424-1046-COT26 | M64: COSTO | N64: FIJO | O64: Transferencia a: A. Gabrochile Spa (gestión social) | P64: Transferencia a: A. Gabrochile Spa (gestión social Viña) | S64: x
B65: PENDIENTE | C65: 0308 11871585 | D65: DLOCAL*GOOGLE ADS SANTIAGO | E65: 46235 | F65: BCI | G65: Credito | H65: =K65/1.19 -> 6046.2185 | I65: =H65*19% -> 1148.7815 | J65: 0 | K65: 7195 | L65: GENERAL | M65: GASTO | N65: VARIABLE | O65: DLOCAL*GOOGLE ADS SANTIAGO | P65: 2026-08-27_Movimientos_Tarjeta_5645_SERVICIOS DE INGENIERIA IVAN ANDRES ARRIAGADA BASCUNAN EIRL (1).pdf
A66: FACTURA | B66: PENDIENTE | C66: 20387804 | D66: IMPERIAL S.A. | E66: 46234 | H66: 25639 | I66: 4871 | J66: 0 | K66: =H66+I66 -> 30510 | L66: 0.7 Taller coquimbo 2446-584-COT26 | M66: COSTO | N66: VARIABLE | O66: Materiales de trabajo | P66: IMPERIAL S.A. F_0020387804 | S66: x
A67: BOLETA DE HONORARIOS | B67: CONCILIADO | C67: 6 | D67: Pago : Angel Hernan Pizarro | E67: 46234 | F67: B Chile | G67: Debito | H67: 650000 | I67: 0 | J67: 116962 | K67: =H67+J67 -> 766962 | L67: GENERAL | M67: GASTO | N67: FIJO | O67: Boleta de honorarios - Angel Hernan Pizarro | P67: BOLETA DE HONORARIOS ELECTRONICA N°6 AHPP | S67: x
A68: BOLETA DE HONORARIOS | B68: CONCILIADO | C68: 91 | D68: Pago: Camila Fernanda Morales | E68: 46233 | F68: B Chile | G68: Debito | H68: 300000 | I68: 0 | J68: 53982 | K68: =H68+J68 -> 353982 | L68: 0.3 Licanten 3299-23-L126 | M68: COSTO | N68: FIJO | O68: Boleta de honorarios - Camila Fernada Morales | P68: BOLETA DE HONORARIOS ELECTRONICA N°91 CFMS | S68: x
B69: PENDIENTE | D69: Compra con Tarjeta de Débito en EASY | E69: 46233 | F69: BCI | G69: Debito | H69: =K69/1.19 -> 25201.681 | I69: =H69*19% -> 4788.3193 | J69: 0 | K69: 29990 | L69: GENERAL | M69: GASTO | N69: VARIABLE | O69: Compra con Tarjeta de Débito en EASY | P69: Cartola_Zoron_cte_julio.pdf
B70: PENDIENTE | D70: Compra con Tarjeta de Débito en ESTACIONAMIENTO REPUBLIC | E70: 46233 | F70: BCI | G70: Debito | H70: =K70/1.19 -> 1638.6555 | I70: =H70*19% -> 311.34454 | J70: 0 | K70: 1950 | L70: GENERAL | M70: GASTO | N70: VARIABLE | O70: Compra con Tarjeta de Débito en ESTACIONAMIENTO REPUBLIC | P70: Cartola_Zoron_cte_julio.pdf
B71: PENDIENTE | D71: Compra con Tarjeta de Débito en SODIMAC | E71: 46233 | F71: BCI | G71: Debito | H71: =K71/1.19 -> 126411.76 | I71: =H71*19% -> 24018.235 | J71: 0 | K71: 150430 | L71: GENERAL | M71: GASTO | N71: VARIABLE | O71: Compra con Tarjeta de Débito en SODIMAC | P71: Cartola_Zoron_cte_julio.pdf
B72: PENDIENTE | C72: 3107 00102011 | D72: DL*GOOGLE ADS SANTIAGO | E72: 46233 | F72: BCI | G72: Credito | H72: =K72/1.19 -> 50420.168 | I72: =H72*19% -> 9579.8319 | J72: 0 | K72: 60000 | L72: GENERAL | M72: GASTO | N72: VARIABLE | O72: DL*GOOGLE ADS SANTIAGO | P72: 2026-08-27_Movimientos_Tarjeta_5645_SERVICIOS DE INGENIERIA IVAN ANDRES ARRIAGADA BASCUNAN EIRL (7).pdf
A73: FACTURA | B73: PENDIENTE | C73: 49 | D73: Agencia Eudora Spa | E73: 46231 | H73: 700000 | I73: 133000 | J73: 0 | K73: =H73+I73 -> 833000 | L73: GENERAL | M73: GASTO | N73: VARIABLE | O73: Servicio de Marketing Digital e IA | P73: F_49 AGENCIA EUDORA SPA | S73: x
A74: BOLETA DE HONORARIOS | B74: CONCILIADO | C74: 16 | D74: Pago: Catalina Badilla | E74: 46231 | F74: B Chile | G74: Debito | H74: 40000 | I74: 0 | J74: 7198 | K74: =H74+J74 -> 47198 | L74: 0.5 San Carlos 2724-454-COT26 | M74: COSTO | N74: FIJO | O74: Boleta de honorarios - Catalina Badilla | P74: BOLETA DE HONORARIOS ELECTRONICA N°16 CIBB | S74: x
B75: PENDIENTE | C75: 2407 11250245 | D75: DLOCAL*GOOGLE ADS SANTIAGO | E75: 46226 | F75: BCI | G75: Credito | H75: =K75/1.19 -> 25210.084 | I75: =H75*19% -> 4789.916 | J75: 0 | K75: 30000 | L75: GENERAL | M75: GASTO | N75: VARIABLE | O75: DLOCAL*GOOGLE ADS SANTIAGO | P75: 2026-08-27_Movimientos_Tarjeta_5645_SERVICIOS DE INGENIERIA IVAN ANDRES ARRIAGADA BASCUNAN EIRL (7).pdf
B76: PENDIENTE | C76: 2207 24492166 | D76: OPENAI*CHATGPT SUB - Internacional | E76: 46225 | F76: BCI | G76: Credito | H76: =K76/1.19 -> 15580.84 | I76: =H76*19% -> 2960.3597 | J76: 0 | K76: 18541.2 | L76: GENERAL | M76: GASTO | N76: FIJO | O76: OPENAI*CHATGPT SUB - Internacional | P76: 2026-08-27_Movimientos_Tarjeta_5645_SERVICIOS DE INGENIERIA IVAN ANDRES ARRIAGADA BASCUNAN EIRL (8).pdf
A77: FACTURA | B77: PENDIENTE | C77: 53768820 | D77: Entel servicios de ingenieria Ivan Andres Arriagada | E77: 46223 | H77: --- | I77: --- | J77: --- | K77: --- | L77: GENERAL | M77: GASTO | N77: FIJO | O77: Servicio publico telefonico | P77: F_53768820 ENTEL FIJO | S77: x
A78: FACTURA | B78: PENDIENTE | C78: 21591468 | D78: =D79 -> Suscripcion mensual | E78: 46223 | H78: 17905 | I78: 3402 | J78: 0 | K78: =H78+I78 -> 21307 | L78: GENERAL | M78: GASTO | N78: FIJO | O78: =O79 -> Pago credito | P78: F_21591468 ENTEL | S78: x
A79: FACTURA | B79: PENDIENTE | C79: 16139 | D79: Suscripcion mensual | E79: 46220 | G79: Credito | H79: 71887 | I79: 13659 | J79: 0 | K79: =H79+I79 -> 85546 | L79: GENERAL | M79: GASTO | N79: FIJO | O79: Pago credito | P79: F_16139 LICITALAB - PLAN CRECE JULIO 17 | S79: x
B80: PENDIENTE | C80: 1507 24011346 | D80: ANTHROPIC* CLAUDE S - Internacional | E80: 46218 | F80: BCI | G80: Credito | H80: =K80/1.19 -> 18541.202 | I80: =H80*19% -> 3522.8283 | J80: 0 | K80: 22064.03 | L80: GENERAL | M80: GASTO | N80: FIJO | O80: ANTHROPIC* CLAUDE S | P80: 2026-08-27_Movimientos_Tarjeta_5645_SERVICIOS DE INGENIERIA IVAN ANDRES ARRIAGADA BASCUNAN EIRL (8).pdf
A81: FACTURA | B81: PENDIENTE | C81: 17CJFK4L-0003 | D81: Pago Invoice mensual | E81: 46217 | H81: 18320 | I81: 3500 | J81: 0 | K81: =H81+I81 -> 21820 | L81: GENERAL | M81: GASTO | N81: FIJO | O81: Suscripcion mensual | P81: F_ 17CJFK4L-0003 Invoice Julio 14 | S81: x
A82: BOLETA | B82: PENDIENTE | C82: 438263 | D82: COPEC S.A. | E82: 46213 | G82: Credito | H82: 8776 | I82: 1667 | J82: 0 | K82: =H82+I82+1177 -> 11620 | L82: 0.5 San Carlos 2724-454-COT26 | M82: COSTO | N82: VARIABLE | O82: Combustible | P82: COPEC S.A. BOLETA N°438263 | Q82: Gastos 10.07.2026 San Carlos 2724-454-COT26.pdf
A83: COMPROBANTE DE PAGO | B83: PENDIENTE | D83: Soc. Conc. Ruta 5 Talca-Chillán S.A. | E83: 46213 | G83: Efectivo | H83: 800 | I83: 0 | J83: 0 | K83: 800 | L83: 0.5 San Carlos 2724-454-COT26 | M83: COSTO | N83: VARIABLE | O83: PEAJE Plaza: Chillán Norte | P83: Pago Peaje Plaza Chillán Norte 10-07-26 | Q83: Gastos 10.07.2026 San Carlos 2724-454-COT26.pdf
A84: BOLETA | B84: PENDIENTE | C84: 8897 | D84: Actividades de Restaurantes y de Servicio Movil de Comidas | E84: 46213 | G84: Credito | H84: 5042 | I84: 958 | J84: 0 | K84: =H84+I84 -> 6000 | L84: 0.5 San Carlos 2724-454-COT26 | M84: COSTO | N84: VARIABLE | O84: Alimentación | P84: Actividades de Restaurantes y de Servicio Movil de Comidas BOLETA N°8897 | Q84: Gastos 10.07.2026 San Carlos 2724-454-COT26.pdf
A85: FACTURA | B85: PENDIENTE | C85: 3506078 | D85: Empresa nacional de certificacion electronica - ECERT | E85: 46211 | F85: B Chile | G85: Debito | H85: 3445 | I85: 655 | J85: 0 | K85: =H85+I85 -> 4100 | L85: 0.4 ESTACION CENTRAL 2434-1-LP26 | M85: COSTO | N85: VARIABLE | O85: Firma electronica avanzada online de un solo uso | P85: ECERT F_3506078 | Q85: 08-07 Comprobante de Pago Firma Electrónica Estación Central | S85: x
A86: BOLETA | B86: PENDIENTE | C86: 32312811 | D86: Ruta pass pago peajes de ruta | E86: 46210 | L86: GENERAL | P86: BOLETA RUTA PASS N°32312811 | S86: x
B87: PENDIENTE | C87: 0707 00000000 | D87: TRASPASO DEUDA INTERNACIONAL | E87: 46210 | F87: BCI | G87: Credito | H87: =K87/1.19 -> 52663.244 | I87: =H87*19% -> 10006.016 | J87: 0 | K87: 62669.26 | L87: GENERAL | M87: GASTO | N87: VARIABLE | O87: TRASPASO DEUDA INTERNACIONAL | P87: 2026-08-27_Movimientos_Tarjeta_5645_SERVICIOS DE INGENIERIA IVAN ANDRES ARRIAGADA BASCUNAN EIRL (8).pdf
B88: PENDIENTE | D88: Pac Tarjeta De Credito Visa | E88: 46210 | F88: BCI | G88: Debito | H88: =K88/1.19 -> 107666.39 | I88: =H88*19% -> 20456.613 | J88: 0 | K88: 128123 | L88: GENERAL | M88: GASTO | N88: VARIABLE | O88: Pac Tarjeta De Credito Visa | P88: Cartola_Zoron_cte_julio.pdf
A89: FACTURA | B89: PENDIENTE | C89: 21516300 | D89: Entel Servicios de ingenieria Ivan Andres | E89: 46208 | H89: 28168 | I89: 5352 | J89: 0 | K89: =H89+I89 -> 33520 | L89: GENERAL | M89: GASTO | N89: FIJO | O89: =O90 -> Servicio publico telefonico | P89: F_21516300 ENTEL | S89: x
A90: FACTURA | B90: PENDIENTE | C90: 21512257 | D90: Entel servicios de ingenieria Ivan Andres Arriagada | E90: 46204 | H90: 26805 | I90: 5093 | J90: 0 | K90: 31898 | L90: GENERAL | M90: GASTO | N90: FIJO | O90: Servicio publico telefonico | P90: F_21512257 ENTEL FIJO | S90: x
A91: FACTURA | B91: PENDIENTE | C91: 43 | D91: Agencia Eudora Spa | E91: 46204 | F91: B Chile | G91: Credito | H91: 700000 | I91: 133000 | J91: 0 | K91: =H91+I91 -> 833000 | L91: GENERAL | M91: GASTO | N91: VARIABLE | O91: Servicio de Marketing Digital e IA | P91: F_43 AGENCIA EUDORA SPA | S91: x
B92: PENDIENTE | D92: Transferencia enviada a Ivan Arriagada | E92: 46204 | F92: BCI | G92: Debito | H92: =K92/1.19 -> 420168.07 | I92: =H92*19% -> 79831.933 | J92: 0 | K92: 500000 | L92: GENERAL | M92: GASTO | N92: VARIABLE | O92: Transferencia enviada a Ivan Arriagada | P92: Cartola_Zoron_cte_junio_26.pdf
A93: BOLETA DE HONORARIOS | B93: CONCILIADO | C93: 90 | D93: Pago: Camila Fernanda Morales | E93: 46203 | F93: B Chile | G93: Debito | H93: 300000 | I93: 0 | J93: 53982 | K93: =H93+J93 -> 353982 | L93: 0.3 Licanten 3299-23-L126 | M93: COSTO | N93: FIJO | O93: Boleta de honorarios - Camila Fernada Morales | P93: BOLETA DE HONORARIOS ELECTRONICA N°90 CFMS | S93: x
A94: BOLETA DE HONORARIOS | B94: PENDIENTE | C94: 17 | D94: Pago: Juan Eduardo Castro | E94: 46203 | F94: B Chile | G94: Debito | H94: 275000 | I94: 0 | J94: 49484 | K94: =H94+J94 -> 324484 | L94: GENERAL | M94: GASTO | N94: FIJO | O94: Boleta de honorarios - Juan Eduardo Castro | P94: BOLETA DE HONORARIOS ELECTRONICA N°17 JECV | S94: x
A95: BOLETA DE HONORARIOS | B95: CONCILIADO | C95: 14 | D95: Pago: Catalina Badilla | E95: 46203 | F95: B Chile | G95: Debito | H95: 40000 | I95: 0 | J95: 7198 | K95: =H95+J95 -> 47198 | L95: 0.5 San Carlos 2724-454-COT26 | M95: COSTO | N95: FIJO | O95: Boleta de honorarios - Catalina Badilla | P95: BOLETA DE HONORARIOS ELECTRONICA N°14 CIBB | S95: x
A96: COMPROBANTE DE PAGO | B96: PENDIENTE | D96: Soc. Conc. Ruta 5 Talca-Chillán S.A. | E96: 46197 | G96: Efectivo | H96: 800 | I96: 0 | J96: 0 | K96: 800 | L96: 0.5 San Carlos 2724-454-COT26 | M96: COSTO | N96: VARIABLE | O96: PEAJE Plaza: Chillán Norte | P96: Pago Peaje Plaza Chillán Norte 24-06-26 | Q96: Gastos 24.06.2026.pdf
A97: COMPROBANTE DE PAGO | B97: PENDIENTE | D97: Soc. Conc. Ruta 5 Talca-Chillán S.A. | E97: 46197 | G97: Efectivo | H97: 800 | I97: 0 | J97: 0 | K97: 800 | L97: 0.5 San Carlos 2724-454-COT26 | M97: COSTO | N97: VARIABLE | O97: PEAJE Plaza Lateral San Carlos Sur | P97: Pago Peaje Plaza Lateral San Carlos Sur 24-06-26 | Q97: Gastos 24.06.2026.pdf
A98: BOLETA | B98: PENDIENTE | C98: 11931895 | D98: Empresa Nacional de Energía ENEX S.A | E98: 46197 | G98: Debito | H98: 8131 | I98: =H98*19% -> 1544.89 | J98: 0 | K98: =H98+I98+860 -> 10535.89 | L98: 0.5 San Carlos 2724-454-COT26 | M98: COSTO | N98: VARIABLE | O98: Combustible | P98: ENEX S.A. BOLETA N°11931895 | Q98: Gastos 24.06.2026.pdf | S98: x
B99: PENDIENTE | C99: 2206 24492166 | D99: OPENAI*CHATGPT SUB - Internacional | E99: 46195 | F99: BCI | G99: Credito | H99: =K99/1.19 -> 15580.84 | I99: =H99*19% -> 2960.3597 | J99: 0 | K99: 18541.2 | L99: GENERAL | M99: GASTO | N99: FIJO | O99: OPENAI*CHATGPT SUB - Internacional | P99: 2026-08-27_Movimientos_Tarjeta_5645_SERVICIOS DE INGENIERIA IVAN ANDRES ARRIAGADA BASCUNAN EIRL (7).pdf
A100: FACTURA | B100: PENDIENTE | C100: 53680645 | D100: Entel servicios de ingenieria Ivan Andres Arriagada | E100: 46193 | H100: --- | I100: --- | J100: --- | K100: --- | L100: GENERAL | M100: GASTO | N100: FIJO | O100: Servicio publico telefonico | P100: F_53680645 ENTEL FIJO | S100: x
...

Sheet Flujo de caja 2025
B4: Saldo de alerta
B5: Pendiente | C5: Pendiente | D5: Pendiente | E5: Pendiente | F5: Pendiente | G5: Pendiente | H5: Pendiente | I5: Pendiente | J5: Pendiente | K5: Pendiente | L5: Pendiente | M5: Pendiente | N5: Pendiente | O5: Pendiente | P5: Pendiente | Q5: Pendiente | R5: Pendiente | S5: Pendiente | T5: Pendiente | U5: Pendiente | V5: Pendiente | W5: Pendiente | X5: Pendiente | Y5: Pendiente | Z5: Pendiente | AA5: Pendiente | AB5: Pendiente | AC5: Pendiente | AD5: Pendiente | AE5: Pendiente | AF5: Pendiente | AG5: Pendiente | AH5: Pendiente | AI5: Pendiente | AJ5: Pendiente | AK5: Pendiente | AL5: Pendiente | AM5: Pendiente | AN5: Pendiente | AO5: Pendiente | AP5: Pendiente | AQ5: Pendiente | AR5: Pendiente | AS5: Pendiente | AT5: Pendiente | AU5: Pendiente | AV5: Pendiente | AW5: Pendiente | AX5: Pendiente | AY5: Pendiente | AZ5: Pendiente | BA5: Pendiente | BB5: Pendiente
A6: Mes | B6: ENERO | C6: ENERO | D6: ENERO | E6: ENERO | F6: ENERO | G6: Febrero | H6: Febrero | I6: Febrero | J6: Febrero | K6: Marzo | L6: Marzo | M6: Marzo | N6: Marzo | O6: Abril | P6: Abril | Q6: Abril | R6: Abril | S6: Mayo | T6: Mayo | U6: Mayo | V6: Mayo | W6: Mayo | X6: Junio | Y6: Junio | Z6: Junio | AA6: Junio | AB6: Julio | AC6: Julio | AD6: Julio | AE6: Julio | AF6: Julio | AG6: Agosto | AH6: Agosto | AI6: Agosto | AJ6: Agosto | AK6: Septiembre | AL6: Septiembre | AM6: Septiembre | AN6: Septiembre | AO6: Octubre | AP6: Octubre | AQ6: Octubre | AR6: Octubre | AS6: Octubre | AT6: Noviembre | AU6: Noviembre | AV6: Noviembre | AW6: Noviembre | AX6: Diciembre | AY6: Diciembre | AZ6: Diciembre | BA6: Diciembre | BB6: Diciembre
A7: Fecha de inicio
A8: Fecha de término
A9: Saldo inicial | C9: =B25 -> 0 | D9: =C25 -> 0 | E9: =D25 -> 0 | F9: =E25 -> 0 | G9: =F25 -> 0 | H9: =G25 -> 0 | I9: =H25 -> 0 | J9: =I25 -> 0 | ... BB9: =BA25 -> 0
A11: Ingresos | B11: Semana 1 | C11: Semana 2 | D11: Semana 3 | E11: Semana 4 | F11: Semana 5 | G11: Semana 6 | H11: Semana 7 | I11: Semana 8 | J11: Semana 9 | K11: Semana 10 | L11: Semana 11 | M11: Semana 12 | N11: Semana 13 | O11: Semana 14 | P11: Semana 15 | Q11: Semana 16 | R11: Semana 17 | S11: Semana 18 | T11: Semana 19 | U11: Semana 20 | V11: Semana 21 | W11: Semana 22 | X11: Semana 23 | Y11: Semana 24 | Z11: Semana 25 | AA11: Semana 26 | AB11: Semana 27 | AC11: Semana 28 | AD11: Semana 29 | AE11: Semana 30 | AF11: Semana 31 | AG11: Semana 32 | AH11: Semana 33 | AI11: Semana 34 | AJ11: Semana 35 | AK11: Semana 36 | AL11: Semana 37 | AM11: Semana 38 | AN11: Semana 39 | AO11: Semana 40 | AP11: Semana 41 | AQ11: Semana 42 | AR11: Semana 43 | AS11: Semana 44 | AT11: Semana 45 | AU11: Semana 46 | AV11: Semana 47 | AW11: Semana 48 | AX11: Semana 49 | AY11: Semana 50 | AZ11: Semana 51 | BA11: Semana 52 | BB11: Semana 53
A12: Ingresos totales | B12: =B13+B14 -> 0 | C12: =SUM(C13:C14) -> 0 | D12: =SUM(D13:D14) -> 0 | E12: =SUM(E13:E14) -> 0 | F12: =SUM(F13:F14) -> 0 | G12: =SUM(G13:G14) -> 0 | H12: =SUM(H13:H14) -> 0 | I12: =SUM(I13:I14) -> 0 | J12: =SUM(J13:J14) -> 0 | ... BB12: =SUM(BB13:BB14) -> 0
A13: Operacionales
A14: NO operacionales
A16: Egresos | B16: Semana 1 | C16: Semana 2 | D16: Semana 3 | E16: Semana 4 | F16: Semana 5 | G16: Semana 6 | H16: Semana 7 | I16: Semana 8 | J16: Semana 9 | K16: Semana 10 | L16: Semana 11 | M16: Semana 12 | N16: Semana 13 | O16: Semana 14 | P16: Semana 15 | Q16: Semana 16 | R16: Semana 17 | S16: Semana 18 | T16: Semana 19 | U16: Semana 20 | V16: Semana 21 | W16: Semana 22 | X16: Semana 23 | Y16: Semana 24 | Z16: Semana 25 | AA16: Semana 26 | AB16: Semana 27 | AC16: Semana 28 | AD16: Semana 29 | AE16: Semana 30 | AF16: Semana 31 | AG16: Semana 32 | AH16: Semana 33 | AI16: Semana 34 | AJ16: Semana 35 | AK16: Semana 36 | AL16: Semana 37 | AM16: Semana 38 | AN16: Semana 39 | AO16: Semana 40 | AP16: Semana 41 | AQ16: Semana 42 | AR16: Semana 43 | AS16: Semana 44 | AT16: Semana 45 | AU16: Semana 46 | AV16: Semana 47 | AW16: Semana 48 | AX16: Semana 49 | AY16: Semana 50 | AZ16: Semana 51 | BA16: Semana 52 | BB16: Semana 53
A17: Egresos totales | B17: =B18+B19+B20+B21 -> 0 | C17: =SUM(C18:C21) -> 0 | D17: =SUM(D18:D21) -> 0 | E17: =SUM(E18:E21) -> 0 | F17: =SUM(F18:F21) -> 0 | G17: =SUM(G18:G21) -> 0 | H17: =SUM(H18:H21) -> 0 | I17: =SUM(I18:I21) -> 0 | J17: =SUM(J18:J21) -> 0 | ... BB17: =SUM(BB18:BB21) -> 0
A18: Costo fijo
A19: Costo variable
A20: Gasto fijo
A21: Gasto variable
A23: Saldo | B23: Semana 1 | C23: Semana 2 | D23: Semana 3 | E23: Semana 4 | F23: Semana 5 | G23: Semana 6 | H23: Semana 7 | I23: Semana 8 | J23: Semana 9 | K23: Semana 10 | L23: Semana 11 | M23: Semana 12 | N23: Semana 13 | O23: Semana 14 | P23: Semana 15 | Q23: Semana 16 | R23: Semana 17 | S23: Semana 18 | T23: Semana 19 | U23: Semana 20 | V23: Semana 21 | W23: Semana 22 | X23: Semana 23 | Y23: Semana 24 | Z23: Semana 25 | AA23: Semana 26 | AB23: Semana 27 | AC23: Semana 28 | AD23: Semana 29 | AE23: Semana 30 | AF23: Semana 31 | AG23: Semana 32 | AH23: Semana 33 | AI23: Semana 34 | AJ23: Semana 35 | AK23: Semana 36 | AL23: Semana 37 | AM23: Semana 38 | AN23: Semana 39 | AO23: Semana 40 | AP23: Semana 41 | AQ23: Semana 42 | AR23: Semana 43 | AS23: Semana 44 | AT23: Semana 45 | AU23: Semana 46 | AV23: Semana 47 | AW23: Semana 48 | AX23: Semana 49 | AY23: Semana 50 | AZ23: Semana 51 | BA23: Semana 52 | BB23: Semana 53
A24: Saldo semanal | B24: =B12-B17 -> 0 | C24: =C12-C17 -> 0 | D24: =D12-D17 -> 0 | E24: =E12-E17 -> 0 | F24: =F12-F17 -> 0 | G24: =G12-G17 -> 0 | H24: =H12-H17 -> 0 | I24: =I12-I17 -> 0 | ... BB24: =BB12-BB17 -> 0
A25: Saldo acumulado | B25: =B9+B12-B17 -> 0 | C25: =C9+C12-C17 -> 0 | D25: =D9+D12-D17 -> 0 | E25: =E9+E12-E17 -> 0 | F25: =F9+F12-F17 -> 0 | G25: =G9+G12-G17 -> 0 | H25: =H9+H12-H17 -> 0 | I25: =I9+I12-I17 -> 0 | ... BB25: =BB9+BB12-BB17 -> 0
A26: Saldo inicial | B26: =B9 | C26: =C9 -> 0 | D26: =D9 -> 0 | E26: =E9 -> 0 | F26: =F9 -> 0 | G26: =G9 -> 0 | H26: =H9 -> 0 | I26: =I9 -> 0 | ... BB26: =BB9 -> 0
Q28: x

Sheet Flujo de caja 2026
B4: Saldo de alerta
B5: Pendiente | C5: Pendiente | D5: Pendiente | E5: Pendiente | F5: Pendiente | G5: Pendiente | H5: Pendiente | I5: Pendiente | J5: Pendiente | K5: Pendiente | L5: Pendiente | M5: Pendiente | N5: Pendiente | O5: Pendiente | P5: Pendiente | Q5: Pendiente | R5: Pendiente | S5: Pendiente | T5: Pendiente | U5: Pendiente | V5: Pendiente | W5: Pendiente | X5: Pendiente | Y5: Pendiente | Z5: Pendiente | AA5: Pendiente | AB5: Pendiente | AC5: Pendiente | AD5: Pendiente | AE5: Pendiente | AF5: Pendiente | AG5: Pendiente | AH5: Pendiente | AI5: Pendiente | AJ5: Pendiente | AK5: Pendiente | AL5: Pendiente | AM5: Pendiente | AN5: Pendiente | AO5: Pendiente | AP5: Pendiente | AQ5: Pendiente | AR5: Pendiente | AS5: Pendiente | AT5: Pendiente | AU5: Pendiente | AV5: Pendiente | AW5: Pendiente | AX5: Pendiente | AY5: Pendiente | AZ5: Pendiente | BA5: Pendiente | BB5: Pendiente
A6: Mes | B6: ENERO | C6: ENERO | D6: ENERO | E6: ENERO | F6: ENERO | G6: Febrero | H6: Febrero | I6: Febrero | J6: Febrero | K6: Marzo | L6: Marzo | M6: Marzo | N6: Marzo | O6: Abril | P6: Abril | Q6: Abril | R6: Abril | S6: Mayo | T6: Mayo | U6: Mayo | V6: Mayo | W6: Mayo | X6: Junio | Y6: Junio | Z6: Junio | AA6: Junio | AB6: Julio | AC6: Julio | AD6: Julio | AE6: Julio | AF6: Julio | AG6: Agosto | AH6: Agosto | AI6: Agosto | AJ6: Agosto | AK6: Septiembre | AL6: Septiembre | AM6: Septiembre | AN6: Septiembre | AO6: Octubre | AP6: Octubre | AQ6: Octubre | AR6: Octubre | AS6: Octubre | AT6: Noviembre | AU6: Noviembre | AV6: Noviembre | AW6: Noviembre | AX6: Diciembre | AY6: Diciembre | AZ6: Diciembre | BA6: Diciembre | BB6: Diciembre
A7: Fecha de inicio | B7: 46020 | C7: 46027 | D7: 46034 | E7: 46041 | F7: 46048 | G7: 46055 | H7: 46062 | I7: 46069 | J7: 46076 | K7: 46083 | L7: 46090 | M7: 46097 | N7: 46104 | O7: 46111 | P7: 46118 | Q7: 46125 | R7: 46132 | S7: 46139 | T7: 46146 | U7: 46153 | V7: 46160 | W7: 46167 | X7: 46174 | Y7: 46181 | Z7: 46188 | AA7: 46195 | AB7: 46202 | AC7: 46209 | AD7: 46216 | AE7: 46223 | AF7: 46230 | AG7: 46237 | AH7: 46244 | AI7: 46251 | AJ7: 46258 | AK7: 46265 | AL7: 46272 | AM7: 46279 | AN7: 46286 | AO7: 46293 | AP7: 46300 | AQ7: 46307 | AR7: 46314 | AS7: 46321 | AT7: 46328 | AU7: 46335 | AV7: 46342 | AW7: 46349 | AX7: 46356 | AY7: 46363 | AZ7: 46370 | BA7: 46377 | BB7: 46384
A8: Fecha de término | B8: 46026 | C8: 46033 | D8: 46040 | E8: 46047 | F8: 46054 | G8: 46061 | H8: 46068 | I8: 46075 | J8: 46082 | K8: 46089 | L8: 46096 | M8: 46103 | N8: 46110 | O8: 46117 | P8: 46124 | Q8: 46131 | R8: 46138 | S8: 46145 | T8: 46152 | U8: 46159 | V8: 46166 | W8: 46173 | X8: 46180 | Y8: 46187 | Z8: 46194 | AA8: 46201 | AB8: 46208 | AC8: 46215 | AD8: 46222 | AE8: 46229 | AF8: 46236 | AG8: 46243 | AH8: 46250 | AI8: 46257 | AJ8: 46264 | AK8: 46271 | AL8: 46278 | AM8: 46285 | AN8: 46292 | AO8: 46299 | AP8: 46306 | AQ8: 46313 | AR8: 46320 | AS8: 46327 | AT8: 46334 | AU8: 46341 | AV8: 46348 | AW8: 46355 | AX8: 46362 | AY8: 46369 | AZ8: 46376 | BA8: 46383 | BB8: 46390
A9: Saldo inicial | C9: =B25 -> -5328923 | D9: =C25 -> -32015751 | E9: =D25 -> -34746202 | F9: =E25 -> -36715988 | G9: =F25 -> -41758695 | H9: =G25 -> -66183084 | I9: =H25 -> -70717852 | J9: =I25 -> -72785852 | ... BB9: =BA25 -> -89871376
A11: Ingresos | B11: Semana 1 | C11: Semana 2 | D11: Semana 3 | E11: Semana 4 | F11: Semana 5 | G11: Semana 6 | H11: Semana 7 | I11: Semana 8 | J11: Semana 9 | K11: Semana 10 | L11: Semana 11 | M11: Semana 12 | N11: Semana 13 | O11: Semana 14 | P11: Semana 15 | Q11: Semana 16 | R11: Semana 17 | S11: Semana 18 | T11: Semana 19 | U11: Semana 20 | V11: Semana 21 | W11: Semana 22 | X11: Semana 23 | Y11: Semana 24 | Z11: Semana 25 | AA11: Semana 26 | AB11: Semana 27 | AC11: Semana 28 | AD11: Semana 29 | AE11: Semana 30 | AF11: Semana 31 | AG11: Semana 32 | AH11: Semana 33 | AI11: Semana 34 | AJ11: Semana 35 | AK11: Semana 36 | AL11: Semana 37 | AM11: Semana 38 | AN11: Semana 39 | AO11: Semana 40 | AP11: Semana 41 | AQ11: Semana 42 | AR11: Semana 43 | AS11: Semana 44 | AT11: Semana 45 | AU11: Semana 46 | AV11: Semana 47 | AW11: Semana 48 | AX11: Semana 49 | AY11: Semana 50 | AZ11: Semana 51 | BA11: Semana 52 | BB11: Semana 53
A12: Ingresos totales | B12: =SUM(B13:B14) -> 719585 | C12: =SUM(C13:C14) -> 1868172 | D12: =SUM(D13:D14) -> 2041090 | E12: =SUM(E13:E14) -> 0 | F12: =SUM(F13:F14) -> 0 | G12: =SUM(G13:G14) -> 0 | H12: =SUM(H13:H14) -> 4398 | I12: =SUM(I13:I14) -> 0 | ... BB12: =SUM(BB13:BB14) -> 0
A13: Operacionales | B13: =Registro!K342 -> 719585 | C13: =Registro!K341 -> 39644 | D13: =SUM(Registro!K339:K340) -> 1208090
A14: NO operacionales | C14: =SUM(Registro!K334:K338) -> 1828528 | D14: =Registro!K337 -> 833000 | H14: =Registro!K259+Registro!K263 -> 4398 | J14: =Registro!K226 -> 5500 | K14: =Registro!K289+Registro!K290 -> 530000 | L14: =Registro!K195 -> 204091 | N14: =Registro!K187 -> 39791 | P14: =Registro!K177 -> 58724 | R14: =Registro!K150 -> 200000
A16: Egresos | B16: Semana 1 | C16: Semana 2 | D16: Semana 3 | E16: Semana 4 | F16: Semana 5 | G16: Semana 6 | H16: Semana 7 | I16: Semana 8 | J16: Semana 9 | K16: Semana 10 | L16: Semana 11 | M16: Semana 12 | N16: Semana 13 | O16: Semana 14 | P16: Semana 15 | Q16: Semana 16 | R16: Semana 17 | S16: Semana 18 | T16: Semana 19 | U16: Semana 20 | V16: Semana 21 | W16: Semana 22 | X16: Semana 23 | Y16: Semana 24 | Z16: Semana 25 | AA16: Semana 26 | AB16: Semana 27 | AC16: Semana 28 | AD16: Semana 29 | AE16: Semana 30 | AF16: Semana 31 | AG16: Semana 32 | AH16: Semana 33 | AI16: Semana 34 | AJ16: Semana 35 | AK16: Semana 36 | AL16: Semana 37 | AM16: Semana 38 | AN16: Semana 39 | AO16: Semana 40 | AP16: Semana 41 | AQ16: Semana 42 | AR16: Semana 43 | AS16: Semana 44 | AT16: Semana 45 | AU16: Semana 46 | AV16: Semana 47 | AW16: Semana 48 | AX16: Semana 49 | AY16: Semana 50 | AZ16: Semana 51 | BA16: Semana 52 | BB16: Semana 53
A17: Egresos totales | B17: =SUM(B18:B21) -> 6048508 | C17: =SUM(C18:C21) -> 28555000 | D17: =SUM(D18:D21) -> 4771540.8 | E17: =SUM(E18:E21) -> 1969786 | F17: =SUM(F18:F21) -> 5042707 | G17: =SUM(G18:G21) -> 24424389 | H17: =SUM(H18:H21) -> 4539166 | I17: =SUM(I18:I21) -> 2068000 | ... BB17: =SUM(BB18:BB21) -> 0
A18: Costo fijo
A19: Costo variable | B19: =SUM(Registro!K293:K296) -> 4143250 | C19: =Registro!K292 -> 300000 | D19: =Registro!K283+Registro!K284+Registro!K286+Registro!K291 -> 1296458 | E19: =Registro!K281 -> 6000
A20: Gasto fijo | B20: =Registro!K280 -> 45258 | C20: =SUM(Registro!K235:K238) -> 8034972 | D20: =SUM(Registro!K275:K279) -> 114371.75 | F20: =Registro!K273+Registro!K274 -> 855886 | G20: =Registro!K261 -> 3973 | H20: =SUM(Registro!K229:K233) -> 208761 | I20: =Registro!K243+Registro!K244 -> 2068000 | K20: =Registro!K196+Registro!K197+Registro!K199+Registro!K200+Registro!K201+Registro!K210+Registro!K211+Registro!K213+Registro!K216+Registro!K219+Registro!K222+Registro!K287+Registro!K288 -> 4681976 | L20: =Registro!K191+Registro!K192+Registro!K194 -> 1907671 | M20: =Registro!K190 -> 100000 | N20: =Registro!K179+Registro!K180+Registro!K181+Registro!K182 -> 201814 | O20: =Registro!K90+Registro!K113+Registro!K120+Registro!K174+Registro!K178 -> 235261 | P20: =SUM(Registro!K172,Registro!K173,Registro!K175) -> 582147 | Q20: =Registro!K160+Registro!K161+Registro!K163+Registro!K165 -> 1484414 | R20: =Registro!K155 -> 39842
A21: Gasto variable | B21: =SUM(Registro!K330:K333) -> 1860000 | C21: =SUM(Registro!K300:K329) -> 20220028 | D21: =SUM(Registro!K315:K325) -> 3360711 | E21: =Registro!K298+Registro!K299+Registro!K313 -> 1963786 | F21: =SUM(Registro!K308:K311) -> 4186821 | G21: =Registro!K297+Registro!K302+Registro!K303+Registro!K304+Registro!K305+Registro!K306+Registro!K307 -> 24420416 | H21: =Registro!K234+Registro!K245+Registro!K258 -> 4330405 | J21: =Registro!K236 -> 1064407 | K21: =Registro!K212+Registro!K198 -> 356487 | N21: =Registro!K188+Registro!K186+Registro!K184 -> 2301185 | P21: =SUM(Registro!K168,Registro!K171,Registro!K169,Registro!K170) -> 886496 | Q21: =Registro!K164 -> 78601 | R21: =SUM(Registro!K146:K148) -> 4203329
A23: Saldo | B23: Semana 1 | C23: Semana 2 | D23: Semana 3 | E23: Semana 4 | F23: Semana 5 | G23: Semana 6 | H23: Semana 7 | I23: Semana 8 | J23: Semana 9 | K23: Semana 10 | L23: Semana 11 | M23: Semana 12 | N23: Semana 13 | O23: Semana 14 | P23: Semana 15 | Q23: Semana 16 | R23: Semana 17 | S23: Semana 18 | T23: Semana 19 | U23: Semana 20 | V23: Semana 21 | W23: Semana 22 | X23: Semana 23 | Y23: Semana 24 | Z23: Semana 25 | AA23: Semana 26 | AB23: Semana 27 | AC23: Semana 28 | AD23: Semana 29 | AE23: Semana 30 | AF23: Semana 31 | AG23: Semana 32 | AH23: Semana 33 | AI23: Semana 34 | AJ23: Semana 35 | AK23: Semana 36 | AL23: Semana 37 | AM23: Semana 38 | AN23: Semana 39 | AO23: Semana 40 | AP23: Semana 41 | AQ23: Semana 42 | AR23: Semana 43 | AS23: Semana 44 | AT23: Semana 45 | AU23: Semana 46 | AV23: Semana 47 | AW23: Semana 48 | AX23: Semana 49 | AY23: Semana 50 | AZ23: Semana 51 | BA23: Semana 52 | BB23: Semana 53
A24: Saldo semanal | B24: =B12-B17 -> -5328923 | C24: =C12-C17 -> -26686828 | D24: =D12-D17 -> -2730450.8 | E24: =E12-E17 -> -1969786 | F24: =F12-F17 -> -5042707 | G24: =G12-G17 -> -24424389 | H24: =H12-H17 -> -4534768 | I24: =I12-I17 -> -2068000 | ... BB24: =BB12-BB17 -> 0
A25: Saldo acumulado | B25: =B9+B12-B17 -> -5328923 | C25: =C9+C12-C17 -> -32015751 | D25: =D9+D12-D17 -> -34746202 | E25: =E9+E12-E17 -> -36715988 | F25: =F9+F12-F17 -> -41758695 | G25: =G9+G12-G17 -> -66183084 | H25: =H9+H12-H17 -> -70717852 | I25: =I9+I12-I17 -> -72785852 | ... BB25: =BB9+BB12-BB17 -> -89871376
A26: Saldo inicial | B26: =B9 | C26: =C9 -> -5328923 | D26: =D9 -> -32015751 | E26: =E9 -> -34746202 | F26: =F9 -> -36715988 | G26: =G9 -> -41758695 | H26: =H9 -> -66183084 | I26: =I9 -> -70717852 | ... BB26: =BB9 -> -89871376
Q28: x

Sheet Ev. KPI Constanza
P2: Indicadores Financieros
P3: Utilidad Operacional | Q3: Margen Operacional | R3: Rentabilidad
P5: =C5-(G5+I5+J5+L5) -> 0 | Q5: =P5/C5 -> #DIV/0! | R5: =P5/(SUM(G5:L5)) -> #DIV/0!
P6: =C6-(G6+I6+J6+L6) -> 160631 | Q6: =P6/C6 -> 0.76261804 | R6: =P6/(SUM(G6:L6)) -> 0.062128548
P7: =C7-(G7+I7+J7+L7) -> -742857 | Q7: =P7/C7 -> #DIV/0! | R7: =P7/(SUM(G7:L7)) -> -1
P8: =C8-(G8+I8+J8+L8) -> 0 | Q8: =P8/C8 -> #DIV/0! | R8: =P8/(SUM(G8:L8)) -> 0
P9: =C9-(G9+I9+J9+L9) -> -80000 | Q9: =P9/C9 -> #DIV/0! | R9: =P9/(SUM(G9:L9)) -> -0.83144526
P10: =C10-(G10+I10+J10+L10) -> 0 | Q10: =P10/C10 -> #DIV/0! | R10: =P10/(SUM(G10:L10)) -> 0
P11: =C11-(G11+I11+J11+L11) -> 0 | Q11: =P11/C11 -> #DIV/0! | R11: =P11/(SUM(G11:L11)) -> 0
A12: 0.8 Gestión Social Viña 2424-1046-COT26 | P12: =C12-(G12+I12+J12+L12) -> -414191.83 | Q12: =P12/C12 -> #DIV/0! | R12: =P12/(SUM(G12:L12)) -> -0.25371475
P13: =C13-(G13+I13+J13+L13) -> -254250 | Q13: =P13/C13 -> #DIV/0! | R13: =P13/(SUM(G13:L13)) -> -0.92373593
P14: =C14-(G14+I14+J14+L14) -> 1366394.9 | Q14: =P14/C14 -> 0.54655795 | R14: =P14/(SUM(G14:L14)) -> 1.0205369
P15: =C15-(G15+I15+J15+L15) -> -72000 | Q15: =P15/C15 -> -0.18947368 | R15: =P15/(SUM(G15:L15)) -> -0.15929204
P16: =C16-(G16+I16+J16+L16) -> 997000 | Q16: =P16/C16 -> 1 | R16: =P16/(SUM(G16:L16)) -> #DIV/0!
P17: =C17-(G17+I17+J17+L17) -> 113166.2 | Q17: =P17/C17 -> 0.13717115 | R17: =P17/(SUM(G17:L17)) -> 0.13904894
P18: =C18-(G18+I18+J18+L18) -> 403951.8 | Q18: =P18/C18 -> 0.96140544 | R18: =P18/(SUM(G18:L18)) -> 9.9701305
P19: =C19-(G19+I19+J19+L19) -> 393726 | Q19: =P19/C19 -> 0.80352245 | R19: =P19/(SUM(G19:L19)) -> 1.550295
P20: =C20-(G20+I20+J20+L20) -> 250000 | Q20: =P20/C20 -> 0.14705882 | R20: =P20/(SUM(G20:L20)) -> 0.17241379
P21: =C21-(G21+I21+J21+L21) -> 550000 | Q21: =P21/C21 -> 1 | R21: =P21/(SUM(G21:L21)) -> #DIV/0!
P22: =C22-(G22+I22+J22+L22) -> 741000 | Q22: =P22/C22 -> 1 | R22: =P22/(SUM(G22:L22)) -> #DIV/0!
P23: =C23-(G23+I23+J23+L23) -> -400350 | Q23: =P23/C23 -> -0.57447266 | R23: =P23/(SUM(G23:L23)) -> -0.36486671
P24: =C24-(G24+I24+J24+L24) -> 13121748 | Q24: =P24/C24 -> 0.75138803 | R24: =P24/(SUM(G24:L24)) -> 1.364029
... P28: =C28-(G28+I28+J28+L28) -> 0 | Q28: =P28/C28 -> #DIV/0! | R28: =P28/(SUM(G28:L28)) -> #DIV/0!
D59: peso | F59: %
D60: 766692 | F60: 1
D61: 116962 | F61: =(D61*F60)/D60 -> 0.15255409

Sheet EV - Alan 
H1: Utilidad operacional | I1: Margen operacional | J1: Rentabilidad
H3: =C17-(B3+C3) -> -1686473 | I3: =H3/C17 -> #DIV/0! | J3: =H3/B3 -> -5.7470932
H4: - | I4: -% | J4: -
H5: =C19-(B5+C5) -> -730038 | I5: =H5/C19 -> #DIV/0! | J5: =H5/B5 -> -6.1112013
H6: =C20-(B6+C6) -> -50020 | I6: =H6/C20 -> #DIV/0! | J6: =H6/B6 -> -1.6673333
H7: - | I7: -% | J7: -%
H8: - | I8: -% | J8: -%
H9: - | I9: -% | J9: -%
H10: - | I10: -% | J10: -%
H11: =C23-(B11+C11) -> -9823379 | I11: =H11/C23 -> #DIV/0! | J11: =H11/B11 -> -2.1006725
A14: TOTALES NETOS
